snipes/__init__.py
snipes-0.0.1.dist-info/METADATA
snipes-0.0.1.dist-info/RECORD
snipes-0.0.1.dist-info/WHEEL
snipes-0.0.1.dist-info/top_level.txt
